sealan_sdk/__init__.py
sealan_sdk/v1/__init__.py
sealan_sdk/v1/client.py
sealan_sdk/v1/device.py
sealan_sdk/v1/response.py
sealan_sdk/v1/sim.py
sealan_sdk-0.1.6.dist-info/METADATA
sealan_sdk-0.1.6.dist-info/WHEEL
sealan_sdk-0.1.6.dist-info/top_level.txt
sealan_sdk-0.1.6.dist-info/RECORD
