Metadata-Version: 2.1
Name: sealan-sdk
Version: 0.1.6
Summary: Sealan Cloud SDK for Python
Home-page: https://github.com/sealan-cloud/sealan-sdk-python
Author: Sealan Cloud
Maintainer-email: zhong@sealan.tech
License: Apache License 2.0
Platform: any
Classifier: Development Status :: 5 - Production/Stable
Classifier: Intended Audience :: Developers
Classifier: License :: OSI Approved :: Apache Software License
Classifier: Programming Language :: Python
Classifier: Programming Language :: Python :: 3
Classifier: Programming Language :: Python :: 3.6
Classifier: Programming Language :: Python :: 3.7
Classifier: Programming Language :: Python :: 3.8
Classifier: Programming Language :: Python :: 3.9
Requires-Dist: requests (>=2.26.0)
